pd_extras/__init__.py
pd_extras/check/__init__.py
pd_extras/check/sanitize.py
pd_extras/extra/__init__.py
pd_extras/extra/flattener.py
pd_extras/extra/operations.py
pd_extras/optimize/__init__.py
pd_extras/optimize/df_ops.py
pd_extras/write/__init__.py
pd_extras/write/common.py
pd_extras/write/driver.py
pd_extras/write/nosql_writer.py
pd_extras/write/sql_writer.py
pd_extras-6.1.4.dist-info/LICENSE
pd_extras-6.1.4.dist-info/METADATA
pd_extras-6.1.4.dist-info/WHEEL
pd_extras-6.1.4.dist-info/RECORD
