Metadata-Version: 2.1
Name: pd-extras
Version: 6.1.4
Summary: Some utility functions on top of pandas.
Home-page: https://github.com/proafxin/pd-extras
License: MIT
Author: Masum Billal
Author-email: billalmasum93@gmail.com
Requires-Python: >=3.11,<4.0
Classifier: License :: OSI Approved :: MIT License
Classifier: Programming Language :: Python :: 3
Classifier: Programming Language :: Python :: 3.11
Classifier: Programming Language :: Python :: 3.12
Requires-Dist: mysqlclient (>=2.2.4,<3.0.0)
Requires-Dist: pandas (>=1.5.3)
Requires-Dist: psycopg2 (>=2.9.9,<3.0.0)
Requires-Dist: pymongo (>=4.7.1,<5.0.0)
Requires-Dist: pymssql (>=2.3.0,<3.0.0)
Requires-Dist: sqlalchemy (>=2.0.30,<3.0.0)
Requires-Dist: sqlalchemy-utils (>=0.41.2,<0.42.0)
Project-URL: Documentation, https://pd-extras.readthedocs.io/en/latest/
Project-URL: Repository, https://github.com/proafxin/pd-extras
